cytolncpred/models/model1.pkl
cytolncpred/models/model10.pkl
cytolncpred/models/model11.pkl
cytolncpred/models/model12.pkl
cytolncpred/models/model13.pkl
cytolncpred/models/model14.pkl
cytolncpred/models/model15.pkl
cytolncpred/models/model2.pkl
cytolncpred/models/model3.pkl
cytolncpred/models/model4.pkl
cytolncpred/models/model5.pkl
cytolncpred/models/model6.pkl
cytolncpred/models/model7.pkl
cytolncpred/models/model8.pkl
cytolncpred/models/model9.pkl
cytolncpred/nfeature/Nfeature_DNA.py
cytolncpred/nfeature/Data/DACC.py
cytolncpred/nfeature/Data/MAC.py
cytolncpred/nfeature/Data/TAC.py
cytolncpred/nfeature/Data/pcpsednc.py
cytolncpred/nfeature/Data/pcpsetnc.py
cytolncpred/nfeature/Data/psednc.py
cytolncpred/nfeature/Data/pseknc.py
cytolncpred/nfeature/Data/scpsednc.py
cytolncpred/nfeature/Data/scpsetnc.py
cytolncpred/nfeature/Data/split.py
cytolncpred/nfeature/Data/PaxHeader/DACC.py
cytolncpred/nfeature/Data/PaxHeader/GAC.py
cytolncpred/nfeature/Data/PaxHeader/MAC.py
cytolncpred/nfeature/Data/PaxHeader/TAC.py
cytolncpred/nfeature/Data/PaxHeader/pcpsednc.py
cytolncpred/nfeature/Data/PaxHeader/pcpsetnc.py
cytolncpred/nfeature/Data/PaxHeader/psednc.py
cytolncpred/nfeature/Data/PaxHeader/pseknc.py
cytolncpred/nfeature/Data/PaxHeader/scpsednc.py
cytolncpred/nfeature/Data/PaxHeader/scpsetnc.py
cytolncpred/python_scripts/__init__.py
cytolncpred/python_scripts/cytolncpred.py
cytolncpred-1.2.dist-info/LICENSE
cytolncpred-1.2.dist-info/METADATA
cytolncpred-1.2.dist-info/WHEEL
cytolncpred-1.2.dist-info/entry_points.txt
cytolncpred-1.2.dist-info/top_level.txt
cytolncpred-1.2.dist-info/RECORD
