Metadata-Version: 2.1
Name: cytolncpred
Version: 1.2
Summary: A computational method to predict the probability of lncRNA localizing to cytoplasm
Home-page: https://github.com/raghavagps/cytolncpred
Author: Gajendra P.S. Raghava
Author-email: raghava@iiitd.ac.in
Requires-Python: >=3.8
License-File: LICENSE
Requires-Dist: numpy==2.1.1
Requires-Dist: pandas==2.2.3
Requires-Dist: scikit-learn==1.5.2
Requires-Dist: argparse
Requires-Dist: xgboost==2.1.1
